rtcg/__init__.py
rtcg-0.8.0.dist-info/LICENSE
rtcg-0.8.0.dist-info/METADATA
rtcg-0.8.0.dist-info/WHEEL
rtcg-0.8.0.dist-info/top_level.txt
rtcg-0.8.0.dist-info/RECORD
