Metadata-Version: 2.1
Name: rtcg
Version: 0.8.0
Summary: A runt-time code generator for python
Home-page: https://github.com/carstencodes/rtcg
Author: Carsten Igel
Author-email: cig@bite-that-bit.de
License: BSD-3-Clause
Keywords: code generation
Platform: UNKNOWN
Classifier: Development Status :: 4 - Beta
Classifier: Intended Audience :: Developers
Classifier: License :: OSI Approved :: BSD License
Classifier: Operating System :: OS Independent
Classifier: Programming Language :: Python :: 3.7
Classifier: Programming Language :: Python :: 3.8
Classifier: Programming Language :: Python :: 3.9
Classifier: Topic :: Scientific/Engineering
Classifier: Topic :: Software Development :: Code Generators
Classifier: Topic :: Software Development :: Libraries :: Python Modules
Classifier: Topic :: System
Classifier: Typing :: Typed
Requires-Python: >=3.7, < 4
